play_websocket/__init__.py
play_websocket/providers.py
play_websocket-0.0.2.dist-info/LICENSE
play_websocket-0.0.2.dist-info/METADATA
play_websocket-0.0.2.dist-info/WHEEL
play_websocket-0.0.2.dist-info/entry_points.txt
play_websocket-0.0.2.dist-info/top_level.txt
play_websocket-0.0.2.dist-info/RECORD
