Metadata-Version: 2.1
Name: play-websocket
Version: 0.0.2
Summary: pytest-play support for websockets
Home-page: https://github.com/davidemoro/play_websocket
Author: Davide Moro
Author-email: davide.moro@gmail.com
License: Apache Software License 2.0
Keywords: play_websocket
Platform: UNKNOWN
Classifier: Development Status :: 2 - Pre-Alpha
Classifier: Intended Audience :: Developers
Classifier: License :: OSI Approved :: Apache Software License
Classifier: Natural Language :: English
Classifier: Programming Language :: Python :: 2
Classifier: Programming Language :: Python :: 2.6
Classifier: Programming Language :: Python :: 2.7
Classifier: Programming Language :: Python :: 3
Classifier: Programming Language :: Python :: 3.3
Classifier: Programming Language :: Python :: 3.4
Classifier: Programming Language :: Python :: 3.5
Requires-Dist: pytest-play (>=2.0.0)
Requires-Dist: websocket-client (>=0.16.0)
Provides-Extra: tests
Requires-Dist: pytest ; extra == 'tests'
Requires-Dist: pytest-cov ; extra == 'tests'
